COPYING
COPYING.LESSER
MANIFEST.in
NEWS.rst
README.rst
setup.cfg
setup.py
pyextdirect/__init__.py
pyextdirect/api.py
pyextdirect/configuration.py
pyextdirect/exceptions.py
pyextdirect/infos.py
pyextdirect/router.py
pyextdirect.egg-info/PKG-INFO
pyextdirect.egg-info/SOURCES.txt
pyextdirect.egg-info/dependency_links.txt
pyextdirect.egg-info/top_level.txt
tests/__init__.py
tests/config.py
tests/test_api.py
tests/test_router.py