Metadata-Version: 1.0
Name: pyextdirect
Version: 0.3
Summary: Python implementation of Ext Direct
Home-page: https://github.com/Diaoul/pyextdirect
Author: Antoine Bertin
Author-email: diaoulael@gmail.com
License: LGPLv3
Keywords: ext direct server cgi stack
Platform: UNKNOWN
Classifier: Development Status :: 4 - Beta
Classifier: License :: OSI Approved :: GNU Library or Lesser General Public License (LGPL)
Classifier: Intended Audience :: Developers
Classifier: Operating System :: OS Independent
Classifier: Programming Language :: Python :: 2.6
Classifier: Programming Language :: Python :: 2.7
Classifier: Topic :: Software Development :: Libraries :: Python Modules
